ucscsdk/__init__.py
ucscsdk/ucscbasetype.py
ucscsdk/ucscconstants.py
ucscsdk/ucsccore.py
ucscsdk/ucsccoremeta.py
ucscsdk/ucsccoreutils.py
ucscsdk/ucscdriver.py
ucscsdk/ucsceventhandler.py
ucscsdk/ucscexception.py
ucscsdk/ucscfilter.py
ucscsdk/ucscfiltertype.py
ucscsdk/ucscgenutils.py
ucscsdk/ucschandle.py
ucscsdk/ucscmeta.py
ucscsdk/ucscmethod.py
ucscsdk/ucscmethodfactory.py
ucscsdk/ucscmo.py
ucscsdk/ucscsession.py
ucscsdk/ucscxmlcodec.py
ucscsdk/methodmeta/AaaChangeSelfPasswordMeta.py
ucscsdk/methodmeta/AaaCheckComputeAuthTokenMeta.py
ucscsdk/methodmeta/AaaCheckComputeExtAccessMeta.py
ucscsdk/methodmeta/AaaGetAuthTokenClientMeta.py
ucscsdk/methodmeta/AaaGetAuthTokenInternalMeta.py
ucscsdk/methodmeta/AaaGetComputeAuthTokenMeta.py
ucscsdk/methodmeta/AaaGetKVMLaunchUrlInternalMeta.py
ucscsdk/methodmeta/AaaGetNComputeAuthTokenByDnMeta.py
ucscsdk/methodmeta/AaaGetNComputeAuthTokenInternalByDnMeta.py
ucscsdk/methodmeta/AaaGetRemoteUserRolesMeta.py
ucscsdk/methodmeta/AaaGetUserLocalesMeta.py
ucscsdk/methodmeta/AaaKeepAliveMeta.py
ucscsdk/methodmeta/AaaLoginByTokenMeta.py
ucscsdk/methodmeta/AaaLoginMeta.py
ucscsdk/methodmeta/AaaLogoutMeta.py
ucscsdk/methodmeta/AaaRefreshMeta.py
ucscsdk/methodmeta/AaaTokenLoginMeta.py
ucscsdk/methodmeta/AaaTokenRefreshMeta.py
ucscsdk/methodmeta/CliviewConfMosMeta.py
ucscsdk/methodmeta/ComputeGetQualifiedServersMeta.py
ucscsdk/methodmeta/ComputeGetServerCatalogMeta.py
ucscsdk/methodmeta/ComputeReQualifyMembershipMeta.py
ucscsdk/methodmeta/ConfigCheckHardwareCompatibilityMeta.py
ucscsdk/methodmeta/ConfigCloneMeta.py
ucscsdk/methodmeta/ConfigConfFilteredMeta.py
ucscsdk/methodmeta/ConfigConfMoGroupMeta.py
ucscsdk/methodmeta/ConfigConfMoMeta.py
ucscsdk/methodmeta/ConfigConfMosMeta.py
ucscsdk/methodmeta/ConfigConfRenameMeta.py
ucscsdk/methodmeta/ConfigDeleteMoMeta.py
ucscsdk/methodmeta/ConfigFindDependenciesMeta.py
ucscsdk/methodmeta/ConfigFindDnsByClassIdMeta.py
ucscsdk/methodmeta/ConfigFindPolicyUsageMeta.py
ucscsdk-0.9.0.3.dist-info/AUTHORS.rst
ucscsdk-0.9.0.3.dist-info/LICENSE
ucscsdk-0.9.0.3.dist-info/METADATA
ucscsdk-0.9.0.3.dist-info/WHEEL
ucscsdk-0.9.0.3.dist-info/top_level.txt
ucscsdk-0.9.0.3.dist-info/RECORD
