Metadata-Version: 2.1
Name: ucscsdk
Version: 0.9.0.3
Summary: Python SDK for Cisco Ucs Central
Home-page: https://github.com/ciscoucs/ucscsdk
Author: Cisco Systemc Inc.
Author-email: ucs-python@cisco.com
License: http://www.apache.org/licenses/LICENSE-2.0
Keywords: ucscsdk
Classifier: Development Status :: 4 - Beta
Classifier: Intended Audience :: Developers
Classifier: License :: OSI Approved :: Apache Software License
Classifier: Natural Language :: English
Classifier: Programming Language :: Python :: 2
Classifier: Programming Language :: Python :: 2.6
Classifier: Programming Language :: Python :: 2.7
Classifier: Programming Language :: Python :: 3
Classifier: Programming Language :: Python :: 3.3
Classifier: Programming Language :: Python :: 3.4
Classifier: Programming Language :: Python :: 3.5
License-File: LICENSE
License-File: AUTHORS.rst
Requires-Dist: pyparsing
Requires-Dist: six
Provides-Extra: docs
Requires-Dist: sphinx (<1.3) ; extra == 'docs'
Requires-Dist: sphinxcontrib-napoleon ; extra == 'docs'
Requires-Dist: sphinx-rtd-theme ; extra == 'docs'
Provides-Extra: ssl
Requires-Dist: pyOpenSSL ; extra == 'ssl'
